core/__init__.py
core/auth/__init__.py
core/auth/permissions.py
core/commands/__init__.py
core/commands/base.py
core/constants/__init__.py
core/constants/base.py
core/exceptions/__init__.py
core/exceptions/exception.py
core/exceptions/handler.py
core/middlewares/__init__.py
core/middlewares/authentication.py
core/models/__init__.py
core/models/fields.py
core/models/history.py
core/models/manager.py
core/models/queryset.py
core/models/uuid.py
core/patterns/__init__.py
core/patterns/null.py
core/patterns/saga.py
core/permissions/__init__.py
core/queues/__init__.py
core/queues/base.py
core/renderers/__init__.py
core/renderers/json.py
core/serializers/__init__.py
core/serializers/base.py
core/serializers/fields.py
core/services/__init__.py
core/services/base.py
core/services/proxy.py
core/services/registry.py
core/tests/__init__.py
core/tests/base.py
core/tests/conftest.py
core/utils/__init__.py
core/utils/app.py
core/utils/utils.py
core/views/__init__.py
core/views/base.py
microslac_core-0.0.0.20.dist-info/METADATA
microslac_core-0.0.0.20.dist-info/WHEEL
microslac_core-0.0.0.20.dist-info/RECORD
